MANIFEST.in
setup.py
ajaxuploader/__init__.py
ajaxuploader/models.py
ajaxuploader/urls.py
ajaxuploader.egg-info/PKG-INFO
ajaxuploader.egg-info/SOURCES.txt
ajaxuploader.egg-info/dependency_links.txt
ajaxuploader.egg-info/not-zip-safe
ajaxuploader.egg-info/top_level.txt
ajaxuploader/backends/__init__.py
ajaxuploader/backends/base.py
ajaxuploader/backends/couch.py
ajaxuploader/backends/default_storage.py
ajaxuploader/backends/easy_thumbnails.py
ajaxuploader/backends/local.py
ajaxuploader/backends/mongodb.py
ajaxuploader/backends/s3.py
ajaxuploader/backends/thumbnail.py
ajaxuploader/static/ajaxuploader/css/fileuploader.css
ajaxuploader/static/ajaxuploader/css/loading.gif
ajaxuploader/static/ajaxuploader/js/fileuploader.js
ajaxuploader/templates/ajaxuploader/sample.html
ajaxuploader/tests/__init__.py
ajaxuploader/tests/default_storage_backend.py
ajaxuploader/tests/urls.py
ajaxuploader/views/__init__.py
ajaxuploader/views/base.py
ajaxuploader/views/s3.py