Metadata-Version: 1.0
Name: ajaxuploader
Version: 0.3.4
Summary: AJAX file uploader for django
Home-page: https://github.com/GoodCloud/django-ajax-uploader
Author: Steven Skoczen
Author-email: steven@agoodcloud.com
License: UNKNOWN
Platform: UNKNOWN
